fpindexer/__init__.py
fpindexer/__main__.py
fpindexer/indexer.py
fpindexer/util.py
flashpoint_indexer-1.1.0.dist-info/LICENSE
flashpoint_indexer-1.1.0.dist-info/METADATA
flashpoint_indexer-1.1.0.dist-info/WHEEL
flashpoint_indexer-1.1.0.dist-info/entry_points.txt
flashpoint_indexer-1.1.0.dist-info/top_level.txt
flashpoint_indexer-1.1.0.dist-info/RECORD
