Metadata-Version: 2.1
Name: flashpoint-indexer
Version: 1.1.0
Summary: Creates/Updates an Index of files with hashes in a directory
Home-page: https://github.com/FlashpointProject/FlashpointIndexer
Author: Colin Berry
Author-email: colin.berry.work@gmail.com
License: MIT
Platform: UNKNOWN
Classifier: Environment :: Console
Classifier: License :: OSI Approved :: MIT License
Classifier: Topic :: Software Development :: Libraries :: Python Modules
Classifier: Programming Language :: Python :: 3
Classifier: Programming Language :: Python :: 3.8
Requires-Dist: pyyaml
Requires-Dist: py7zr
